capinvest_cli/__init__.py
capinvest_cli/argparse_translator/__init__.py
capinvest_cli/argparse_translator/argparse_argument.py
capinvest_cli/argparse_translator/argparse_class_processor.py
capinvest_cli/argparse_translator/argparse_translator.py
capinvest_cli/argparse_translator/obbject_registry.py
capinvest_cli/argparse_translator/reference_processor.py
capinvest_cli/argparse_translator/utils.py
capinvest_cli/assets/routines/routine_example.capinvest
capinvest_cli/assets/styles/default/Consolas.ttf
capinvest_cli/assets/styles/default/dark.mpfstyle.json
capinvest_cli/assets/styles/default/dark.mplrc.json
capinvest_cli/assets/styles/default/dark.mplstyle
capinvest_cli/assets/styles/default/dark.pltstyle.json
capinvest_cli/assets/styles/default/dark.richstyle.json
capinvest_cli/assets/styles/default/light.mpfstyle.json
capinvest_cli/assets/styles/default/light.mplrc.json
capinvest_cli/assets/styles/default/light.mplstyle
capinvest_cli/assets/styles/default/light.pltstyle.json
capinvest_cli/assets/styles/default/light.richstyle.json
capinvest_cli/assets/styles/default/tables.pltstyle.json
capinvest_cli/assets/styles/user/openbb.richstyle.json
capinvest_cli/cli.py
capinvest_cli/config/__init__.py
capinvest_cli/config/completer.py
capinvest_cli/config/console.py
capinvest_cli/config/constants.py
capinvest_cli/config/menu_text.py
capinvest_cli/config/setup.py
capinvest_cli/config/style.py
capinvest_cli/controllers/base_controller.py
capinvest_cli/controllers/base_platform_controller.py
capinvest_cli/controllers/choices.py
capinvest_cli/controllers/cli_controller.py
capinvest_cli/controllers/hub_service.py
capinvest_cli/controllers/platform_controller_factory.py
capinvest_cli/controllers/script_parser.py
capinvest_cli/controllers/settings_controller.py
capinvest_cli/controllers/utils.py
capinvest_cli/models/__init__.py
capinvest_cli/models/settings.py
capinvest_cli/session.py
capinvest_cli/utils/__init__.py
capinvest_cli/utils/utils.py
capinvest_cli-1.0.3.dist-info/entry_points.txt
capinvest_cli-1.0.3.dist-info/METADATA
capinvest_cli-1.0.3.dist-info/WHEEL
capinvest_cli-1.0.3.dist-info/RECORD
