Metadata-Version: 2.4
Name: capinvest-cli
Version: 1.0.3
Summary: Investment Research for Everyone, Anywhere.
Author: zbz Team
Requires-Python: >=3.9.21,<3.14
Classifier: Programming Language :: Python :: 3
Classifier: Programming Language :: Python :: 3.10
Classifier: Programming Language :: Python :: 3.11
Classifier: Programming Language :: Python :: 3.12
Classifier: Programming Language :: Python :: 3.13
Requires-Dist: capinvest[all] (>=1.0.1,<2.0.0)
Requires-Dist: openpyxl (>=3.1.5,<4.0.0)
Requires-Dist: prompt-toolkit (>=3.0.50,<4.0.0)
Requires-Dist: python-dotenv (>=1.0.1,<2.0.0)
Requires-Dist: pywry (>=0.6.2,<0.7.0)
Requires-Dist: rich (>=14.0.0,<15.0.0)
